hermes_client_python/__init__.py
hermes_client_python/client.py
hermes_client_python/hermes_pb2.py
hermes_client_python/hermes_pb2_grpc.py
hermes_client_python/types.py
hermes_client_python-1.4.37.dist-info/METADATA
hermes_client_python-1.4.37.dist-info/WHEEL
hermes_client_python-1.4.37.dist-info/RECORD
