Metadata-Version: 2.4
Name: hermes-client-python
Version: 1.4.37
Summary: Async Python client for Hermes search server
Project-URL: Homepage, https://github.com/SpaceFrontiers/hermes
Project-URL: Repository, https://github.com/SpaceFrontiers/hermes
Author: izihawa
License-Expression: MIT
Keywords: async,full-text-search,grpc,search
Classifier: Development Status :: 4 - Beta
Classifier: Intended Audience :: Developers
Classifier: License :: OSI Approved :: MIT License
Classifier: Programming Language :: Python :: 3
Classifier: Programming Language :: Python :: 3.10
Classifier: Programming Language :: Python :: 3.11
Classifier: Programming Language :: Python :: 3.12
Classifier: Programming Language :: Python :: 3.13
Classifier: Topic :: Database :: Database Engines/Servers
Classifier: Topic :: Text Processing :: Indexing
Requires-Python: >=3.10
Requires-Dist: grpcio>=1.76.0
Requires-Dist: protobuf>=6.33.4
